detecta/__init__.py
detecta/detect_cusum.py
detecta/detect_onset.py
detecta/detect_peaks.py
detecta/detect_seq.py
detecta-0.0.5.dist-info/LICENSE
detecta-0.0.5.dist-info/METADATA
detecta-0.0.5.dist-info/WHEEL
detecta-0.0.5.dist-info/top_level.txt
detecta-0.0.5.dist-info/RECORD
