Metadata-Version: 2.1
Name: detecta
Version: 0.0.5
Summary: Detect events in data
Home-page: https://github.com/demotu/detecta
Author: Marcos Duarte
Author-email: duartexyz@gmail.com
License: UNKNOWN
Platform: UNKNOWN
Classifier: Programming Language :: Python :: 3
Classifier: License :: OSI Approved :: MIT License
Classifier: Operating System :: OS Independent
Requires-Python: >=3.6
